{
    "view_title": "Gebruikersprofiel",

    "action_add_page": "Een nieuwe gebruiker toevoegen",

    "name": "Naam",
    "firstname": "Voornaam",
    "infix": "Tussenvoegsel",
    "lastname": "Achternaam",
    "email": "E-mailadres",
    "username": "Gebruikersnaam",
    "password": "Wachtwoord",
    "password_old": "Oude wachtwoord",
    "password_new": "Nieuwe wachtwoord",
    "password_check": "Nogmaals nieuwe wachtwoord",
    "edit_password": "[ bewerken ]",

    "edit_profile_title": "Gebruikersprofiel aanpassen",
    "edit_password_title": "Wachtwoord wijzigen"
}